rdb_py-0.3.0.dist-info/METADATA
rdb_py-0.3.0.dist-info/WHEEL
rdb_py-0.3.0.dist-info/licenses/LICENSE
rdb/__init__.py
rdb/rdb.cpython-311-darwin.so
rdb_py-0.3.0.dist-info/RECORD
