Metadata-Version: 2.4
Name: rdb-py
Version: 0.3.0
Classifier: Programming Language :: Rust
Classifier: Programming Language :: Python :: Implementation :: CPython
Classifier: Programming Language :: Python :: Implementation :: PyPy
Requires-Dist: maturin >=1.8.0
Requires-Dist: cffi ==1.17.1
License-File: LICENSE
Summary: Add your description here
Keywords: redis,database,rdb,parser
Home-Page: http://rdb.fnordig.de/
Author: Jan-Erik Rediger <badboy@fnordig.de>, Tim Bauer <timderbauer@gmail.com>
Author-email: Jan-Erik Rediger <badboy@fnordig.de>, Tim Bauer <timderbauer@gmail.com>
License: MIT
Requires-Python: >=3.10
Project-URL: Source Code, https://github.com/badboy/rdb-rs
